haytool/__init__.py
haytool/audio.py
haytool/dataframe.py
haytool/file_helper.py
haytool/image.py
haytool/json.py
haytool/parallel.py
haytool/string.py
haytool/time.py
haytool-0.0.9.dist-info/LICENSE
haytool-0.0.9.dist-info/METADATA
haytool-0.0.9.dist-info/WHEEL
haytool-0.0.9.dist-info/top_level.txt
haytool-0.0.9.dist-info/RECORD
