Metadata-Version: 2.1
Name: haytool
Version: 0.0.9
Summary: Hayman's toolbox
Author: Hayman
Classifier: Development Status :: 3 - Alpha
Classifier: Intended Audience :: Developers
Classifier: Topic :: Software Development :: Build Tools
Classifier: License :: OSI Approved :: MIT License
Classifier: Programming Language :: Python :: 3
Classifier: Programming Language :: Python :: 3.7
Classifier: Programming Language :: Python :: 3.8
Classifier: Programming Language :: Python :: 3.9
Requires-Python: >=3.6, <4
License-File: LICENSE
Requires-Dist: boto3
Requires-Dist: glog
Requires-Dist: wave
Requires-Dist: pandas
Requires-Dist: pytz
Requires-Dist: requests
